zoochory/__init__.py
zoochory-0.0.1.dist-info/DESCRIPTION.rst
zoochory-0.0.1.dist-info/METADATA
zoochory-0.0.1.dist-info/RECORD
zoochory-0.0.1.dist-info/WHEEL
zoochory-0.0.1.dist-info/entry_points.txt
zoochory-0.0.1.dist-info/metadata.json
zoochory-0.0.1.dist-info/top_level.txt
